Workbook

Sheet Sheet1
A1: Operation | B1: Op-sub_group_id | C1: Operation Sub Group | D1: Value Stream Id | E1: Value Stream Name | F1: Capability Id | G1: Capability Name | H1: Capability Description
A2: =VLOOKUP(B2,Sheet3!B$1:D$42,3,FALSE) -> Customer Experience | B2: =VLOOKUP(C2,Sheet3!A$1:B$42,2,FALSE) -> OP_CX_01 | C2: Customer Experience Management | D2: 1.11 | E2: Customer Experience Analysis | F2: 1.11.1 | G2: Customer Experience Coordination | H2: Customer Experience Coordination represents the cross-channel components that drive consistency and analytics of the customer experience. Channel infrastructure would manage common contact event information such as transaction state, statistics, history, etc.
A3: =VLOOKUP(B3,Sheet3!B$1:D$42,3,FALSE) -> Customer Experience | B3: =VLOOKUP(C3,Sheet3!A$1:B$42,2,FALSE) -> OP_CX_01 | C3: Customer Experience Management | D3: 1.11 | E3: Customer Experience Analysis | F3: 1.11.10 | G3: Customer SLA Violation Notification and Tracking | H3: Customer SLA Violation Notification and Tracking function provides the necessary functionality to notify appropriate people or systems to remedy the SLA violation. to track and manage open Customer SLA issues.
A4: =VLOOKUP(B4,Sheet3!B$1:D$42,3,FALSE) -> Customer Experience | B4: =VLOOKUP(C4,Sheet3!A$1:B$42,2,FALSE) -> OP_CX_01 | C4: Customer Experience Management | D4: 1.11 | E4: Customer Experience Analysis | F4: 1.11.2 | G4: Customer Digital Interaction Tracking | H4: Customer Digital Interaction Tracking Function tracks all user steps on the web site and influence on social networks: click-stream, viewed pages, consulted product descriptions, comments. In real time, this function analyses the user behavior, identifies his centers of interest and then deduces his profile which will be used to push contents and offers adequate for the user / customer needs.
A5: =VLOOKUP(B5,Sheet3!B$1:D$42,3,FALSE) -> Customer Experience | B5: =VLOOKUP(C5,Sheet3!A$1:B$42,2,FALSE) -> OP_CX_01 | C5: Customer Experience Management | D5: 1.11 | E5: Customer Experience Analysis | F5: 1.11.3 | G5: Customer Insights and Closed Loop Automation | H5: Automatically detect customer insights (segmented/collective/individual) and drive decisions regarding customer treatment and action for each specific situation based on observing what the customer is immediately experiencing in a Closed Loop manner. This action can be taken either proactively in real time, or reactively when the customer contacts the Service Provider.
A6: =VLOOKUP(B6,Sheet3!B$1:D$42,3,FALSE) -> Customer Experience | B6: =VLOOKUP(C6,Sheet3!A$1:B$42,2,FALSE) -> OP_CX_01 | C6: Customer Experience Management | D6: 1.11 | E6: Customer Experience Analysis | F6: 1.11.4 | G6: Customer Profile Signature Creation | H6: Customer Profile Signature Creation function creates a personalized profile signature based on combined segment, interest and behavior for the individual “customer” (ex. Soccer Mom, Gold/Silver/Bronze customer, Golfer, Early adopter), and around “content” (ex. Content sharing - College kids + Field Sales). This also includes continuous learning and update of individual ‘Profile Signature’.
A7: =VLOOKUP(B7,Sheet3!B$1:D$42,3,FALSE) -> Customer Experience | B7: =VLOOKUP(C7,Sheet3!A$1:B$42,2,FALSE) -> OP_CX_01 | C7: Customer Experience Management | D7: 1.11 | E7: Customer Experience Analysis | F7: 1.11.5 | G7: Customer Value Segmentation and Profile Prediction | H7: Customer Value Segmentation regroups the customers in relevant sets (even subsets) for Marketing. The segmentation criteria use the customer value, the customer lifetime value, the product and service uses (consumption behaviours). With Profile Prediction, the predictive Scoring of the new customer behavior: using a predictive model based on the histories of customers having similar profiles, determines the expected evolution of the customer value and its lifetime.
A8: =VLOOKUP(B8,Sheet3!B$1:D$42,3,FALSE) -> Customer Experience | B8: =VLOOKUP(C8,Sheet3!A$1:B$42,2,FALSE) -> OP_CX_01 | C8: Customer Experience Management | D8: 1.11 | E8: Customer Experience Analysis | F8: 1.11.6 | G8: Customer Unified Information View | H8: A unified customer data store using various criteria (name, address, subscriber number, equipment id, billing account number, etc.) and finds the customer record to add the new orders, track outstanding orders, progress and history displays.It also links to the predictive customer value score.
A9: =VLOOKUP(B9,Sheet3!B$1:D$42,3,FALSE) -> Customer Experience | B9: =VLOOKUP(C9,Sheet3!A$1:B$42,2,FALSE) -> OP_CX_01 | C9: Customer Experience Management | D9: 1.11 | E9: Customer Experience Analysis | F9: 1.11.7 | G9: Customer Feedback and Satisfaction Reporting | H9: A unified collection, storage and analysis of customer feedback from all touchpoints (including CRM, PoS etc.), Network QoS reports, Predictive Customer Value Score, Customer complaint and online interaction with agent (in person) or self service.
A10: =VLOOKUP(B10,Sheet3!B$1:D$42,3,FALSE) -> Customer Experience | B10: =VLOOKUP(C10,Sheet3!A$1:B$42,2,FALSE) -> OP_CX_01 | C10: Customer Experience Management | D10: 1.11 | E10: Customer Experience Analysis | F10: 1.11.8 | G10: Customer Proactive Issue Detection | H10: Customer Proactive Issue Detection analyses the existing service performance issues or absence of product/services and proposes new services and enhancements according to what the customer presently has. It includes bundling, product proposals, service discounts and compensation in case of service degradation etc.
A11: =VLOOKUP(B11,Sheet3!B$1:D$42,3,FALSE) -> Customer Experience | B11: =VLOOKUP(C11,Sheet3!A$1:B$42,2,FALSE) -> OP_CX_01 | C11: Customer Experience Management | D11: 1.11 | E11: Customer Experience Analysis | F11: 1.11.9 | G11: Customer Proactive and Predictive Care | H11: Outbounbd notification and reach out to customer in case of service disruption or service issue. With Service Degradation Prediction, the outeach iis predictive.
A12: =VLOOKUP(B12,Sheet3!B$1:D$42,3,FALSE) -> Customer Experience | B12: =VLOOKUP(C12,Sheet3!A$1:B$42,2,FALSE) -> OP_CX_01 | C12: Customer Experience Management | D12: 1.12 | E12: Customer Experience Digitalization | F12: 1.12.1 | G12: Self-Help Digital and Call Center Access | H12: Self Help Digital Access and Call Center Access provides access to call center self empowered fulfillment function providing an internet technology driven interface for the customer to undertake a variety of fulfillment functions directly for themselves.
A13: =VLOOKUP(B13,Sheet3!B$1:D$42,3,FALSE) -> Customer Experience | B13: =VLOOKUP(C13,Sheet3!A$1:B$42,2,FALSE) -> OP_CX_02 | C13: Customer Information Management | D13: 1.12 | E13: Customer Experience Digitalization | F13: 1.12.2 | G13: Guided Customer Registration | H13: Customer Registration registers a new customer if this is a new customer (using Customer Information Management). It provides a step by step guide at the channel to capture the specific information items to be collected (e.g. customer identification, required product / order and the pertinent data for the order). Including Validation guidance – for each information element, may provide set of valid input.
... A65: =VLOOKUP(B65,Sheet3!B$1:D$42,3,FALSE) -> Field Operations | B65: =VLOOKUP(C65,Sheet3!A$1:B$42,2,FALSE) -> OP_FO_02 | C65: Work Order Management | D65: 2.1 | E65: Work Order Assignment and Plan | F65: 2.1.5 | G65: Work Order Re-assigning | H65: Initiates re-assignments as needed based on changing priorities, technician progress on other job assignments, etc.
A66: =VLOOKUP(B66,Sheet3!B$1:D$42,3,FALSE) -> Field Operations | B66: =VLOOKUP(C66,Sheet3!A$1:B$42,2,FALSE) -> OP_FO_02 | C66: Work Order Management | D66: 2.2 | E66: Work Order Establishment | F66: 2.2.1 | G66: Work Order Manual Activities Determining | H66: Work Order Manual Activities Determining function provides the necessary functionality to analyze the work order and determine what manual activities are necessary.
A67: =VLOOKUP(B67,Sheet3!B$1:D$42,3,FALSE) -> Field Operations | B67: =VLOOKUP(C67,Sheet3!A$1:B$42,2,FALSE) -> OP_FO_02 | C67: Work Order Management | D67: 2.2 | E67: Work Order Establishment | F67: 2.2.2 | G67: Work Orders Initiation | H67: Work Orders Initiation initiates workforce orders for Network preventive and corrective maintenance and change.
A68: =VLOOKUP(B68,Sheet3!B$1:D$42,3,FALSE) -> Field Operations | B68: =VLOOKUP(C68,Sheet3!A$1:B$42,2,FALSE) -> OP_FO_02 | C68: Work Order Management | D68: 2.3 | E68: Work Order Tracking and Business Value | F68: 2.3.1 | G68: Work Order Closing | H68: Work Order Closing function closes completed work orders
A69: =VLOOKUP(B69,Sheet3!B$1:D$42,3,FALSE) -> Field Operations | B69: =VLOOKUP(C69,Sheet3!A$1:B$42,2,FALSE) -> OP_FO_02 | C69: Work Order Management | D69: 2.3 | E69: Work Order Tracking and Business Value | F69: 2.3.2 | G69: Work Order Information Transferring | H69: Work Order Information Transferring provides information transfer between the operator\\'s workforce management system(s) and those of external third parties (when the infrastructure is owned and operated by third parties).
A70: =VLOOKUP(B70,Sheet3!B$1:D$42,3,FALSE) -> Field Operations | B70: =VLOOKUP(C70,Sheet3!A$1:B$42,2,FALSE) -> OP_FO_02 | C70: Work Order Management | D70: 2.3 | E70: Work Order Tracking and Business Value | F70: 2.3.3 | G70: Work Order Status Monitoring | H70: Monitors the status and progress of the various manual activities, including the various states of the work order
A71: =VLOOKUP(B71,Sheet3!B$1:D$42,3,FALSE) -> Field Operations | B71: =VLOOKUP(C71,Sheet3!A$1:B$42,2,FALSE) -> OP_FO_02 | C71: Work Order Management | D71: 2.3 | E71: Work Order Tracking and Business Value | F71: 2.3.4 | G71: Work Order Updating | H71: Work Order Updating updates the transition of the order through its various states, including in-flight changes and cancellations
A72: =VLOOKUP(B72,Sheet3!B$1:D$42,3,FALSE) -> Field Operations | B72: =VLOOKUP(C72,Sheet3!A$1:B$42,2,FALSE) -> OP_FO_02 | C72: Work Order Management | D72: 2.3 | E72: Work Order Tracking and Business Value | F72: 2.3.5 | G72: Workflow Delay Jeopardy Analyzing | H72: Workflow Delay Jeopardy Analyzing function should be found in any process or workflow management system and warns when a delay in the due date of a task or process step will prevent subsequent tasks from starting, or affect the overall end date of the process, also including escalation function for issues as required.
A73: =VLOOKUP(B73,Sheet3!B$1:D$42,3,FALSE) -> Field Operations | B73: =VLOOKUP(C73,Sheet3!A$1:B$42,2,FALSE) -> OP_FO_01 | C73: Asset Management | D73: 2.4 | E73: Vehicle Fleet Management | F73: 2.4.1 | G73: Fleet Lifecycle and Maintenance Planning | H73: Fleet Lifecycle and Maintenance Planning supports the administration of vehicle financing and vehicle maintenance planning.
A74: =VLOOKUP(B74,Sheet3!B$1:D$42,3,FALSE) -> Field Operations | B74: =VLOOKUP(C74,Sheet3!A$1:B$42,2,FALSE) -> OP_FO_01 | C74: Asset Management | D74: 2.4 | E74: Vehicle Fleet Management | F74: 2.4.2 | G74: Fleet Tracing and Monitoring | H74: Fleet Tracing and Monitoring includes equipment tracing through e.g. vehicle telematics (tracking and diagnostics),
A75: =VLOOKUP(B75,Sheet3!B$1:D$42,3,FALSE) -> Products and Services | B75: =VLOOKUP(C75,Sheet3!A$1:B$42,2,FALSE) -> OP_SO_05 | C75: Security Management | D75: 2.4 | E75: Vehicle Fleet Management | F75: 2.4.3 | G75: Fleet Security and Efficiency Management | H75: Fleet Security and Efficiency Management includes support for driver management, speed management, fuel management and health and safety management.
A76: =VLOOKUP(B76,Sheet3!B$1:D$42,3,FALSE) -> Field Operations | B76: =VLOOKUP(C76,Sheet3!A$1:B$42,2,FALSE) -> OP_FO_01 | C76: Asset Management | D76: 2.4 | E76: Vehicle Fleet Management | F76: 2.4.4 | G76: Fleet Logistic Optimization | H76: Fleet Logistic Optimization provides fleet optimization and risk minimizing through route and utilization planning.
A77: =VLOOKUP(B77,Sheet3!B$1:D$42,3,FALSE) -> Inventory Management | B77: =VLOOKUP(C77,Sheet3!A$1:B$42,2,FALSE) -> OP_IM_01 | C77: Inventory Management | D77: 3.1 | E77: Location Management | F77: 3.1.1 | G77: Location Structure Data Configuration | H77: Location Structure Data Configuration provides facilities for creating, modifying and deleting location structures data according to business rules of Service Providers or national and international location regulations.
... A130: =VLOOKUP(B130,Sheet3!B$1:D$42,3,FALSE) -> Service Operations Center | B130: =VLOOKUP(C130,Sheet3!A$1:B$42,2,FALSE) -> OP_NA_01 | C130: Service Analysis | D130: 5.1 | E130: Service Quality and Performance Analysis | F130: 5.1.2 | G130: Service Performance Root Cause Analyzing | H130: Service Performance Root Cause Analyzing provides support for analyzing of performance data received from Service Performance Monitoring, considering service topology to support determining the root causes of service performance degradations.
A131: =VLOOKUP(B131,Sheet3!B$1:D$42,3,FALSE) -> Service Operations Center | B131: =VLOOKUP(C131,Sheet3!A$1:B$42,2,FALSE) -> OP_NA_01 | C131: Service Analysis | D131: 5.1 | E131: Service Quality and Performance Analysis | F131: 5.1.3 | G131: Service Performance Data Analyzing | H131: Service Performance Data Analyzing provides aggregation and trend analyzing of collected Service Performance Data.
A132: =VLOOKUP(B132,Sheet3!B$1:D$42,3,FALSE) -> Service Operations Center | B132: =VLOOKUP(C132,Sheet3!A$1:B$42,2,FALSE) -> OP_NA_01 | C132: Service Analysis | D132: 5.1 | E132: Service Quality and Performance Analysis | F132: 5.1.4 | G132: Service Performance Event Correlation | H132: Service Performance Event Correlation maps the performance data to service topology and identifies service related performance problems, event filtering included.
A133: =VLOOKUP(B133,Sheet3!B$1:D$42,3,FALSE) -> Service Operations Center | B133: =VLOOKUP(C133,Sheet3!A$1:B$42,2,FALSE) -> OP_NA_01 | C133: Service Analysis | D133: 5.1 | E133: Service Quality and Performance Analysis | F133: 5.1.5 | G133: Service Root Problem Analyzing | H133: Service Root Problem Analyzing provides analysis of customer\\'s present and past problem information by correlation and consolidation of the various customer problems and resource troubles into a single root service problem.
A134: =VLOOKUP(B134,Sheet3!B$1:D$42,3,FALSE) -> Service Operations Center | B134: =VLOOKUP(C134,Sheet3!A$1:B$42,2,FALSE) -> OP_NA_01 | C134: Service Analysis | D134: 5.1 | E134: Service Quality and Performance Analysis | F134: 5.1.6 | G134: Service Quality Analyzing | H134: Service Quality Analyzing function analyzes and evaluates the quality data collected by Service Quality Monitoring, and considering the past service quality data or system environment data in the analysis, notifying operations functions for automatic or manual action in case of alarming analysis results.
A135: =VLOOKUP(B135,Sheet3!B$1:D$42,3,FALSE) -> Service Operations Center | B135: =VLOOKUP(C135,Sheet3!A$1:B$42,2,FALSE) -> OP_NA_01 | C135: Service Analysis | D135: 5.1 | E135: Service Quality and Performance Analysis | F135: 5.1.7 | G135: Service Quality Comparison | H135: Comparison of the collected service quality data to the KQIs and SLOs established by SQM Establishment.
A136: =VLOOKUP(B136,Sheet3!B$1:D$42,3,FALSE) -> Service Operations Center | B136: =VLOOKUP(C136,Sheet3!A$1:B$42,2,FALSE) -> OP_NA_01 | C136: Service Analysis | D136: 5.1 | E136: Service Quality and Performance Analysis | F136: 5.1.8 | G136: Service Quality Improvement Analyzing | H136: Service Quality Improvement Analyzing provides an analyzing function to provide conclusions to relevant areas to make quality improvement proposals.
A137: =VLOOKUP(B137,Sheet3!B$1:D$42,3,FALSE) -> Service Operations Center | B137: =VLOOKUP(C137,Sheet3!A$1:B$42,2,FALSE) -> OP_NA_01 | C137: Service Analysis | D137: 5.1 | E137: Service Quality and Performance Analysis | F137: 5.1.9 | G137: Service Quality Correlation | H137: Provides service quality information correlation from various sources to determine root cause and impact.
A138: =VLOOKUP(B138,Sheet3!B$1:D$42,3,FALSE) -> Service Operations Center | B138: =VLOOKUP(C138,Sheet3!A$1:B$42,2,FALSE) -> OP_NA_03 | C138: Service Problem Management | D138: 5.11 | E138: Service Trouble Analysis | F138: 5.11.1 | G138: Service Problem Diagnose Supporting | H138: Service Problem Diagnose Supporting Function supports the service trouble cause identification via diagnostic actions (Test, inventories and historic consultation, Workforce Intervention) and interpretation rules of their results. The identification of the service trouble cause can be made through: Analysis of associated Service Trouble Ticket Information (first diagnostic) Analysis of Service alarm events (fault of performance data) Issuing service tests, including one time tests or a series of tests over a period of time Analysis of previous service test results, service usage historic, QoS historic, service platform logs, equipment logs, anomaly historic, etc.
A139: =VLOOKUP(B139,Sheet3!B$1:D$42,3,FALSE) -> Service Operations Center | B139: =VLOOKUP(C139,Sheet3!A$1:B$42,2,FALSE) -> OP_NA_03 | C139: Service Problem Management | D139: 5.11 | E139: Service Trouble Analysis | F139: 5.11.2 | G139: Service Problem Resolution | H139: Service Problem Resolution Function supports the identification of the necessary resolution actions, or the best identified solution, to realize to solve the problem.
A140: =VLOOKUP(B140,Sheet3!B$1:D$42,3,FALSE) -> Service Operations Center | B140: =VLOOKUP(C140,Sheet3!A$1:B$42,2,FALSE) -> OP_NA_03 | C140: Service Problem Management | D140: 5.12 | E140: Service Trouble Tracking and Business Value Development | F140: 5.12.1 | G140: Service Trouble Grouping | H140: Service Trouble Grouping Function is in charge of grouping Service Troubles with the same Trouble Cause and of grouping the related Service Trouble Tickets (for example: in case of a collective disturbance).
A141: =VLOOKUP(B141,Sheet3!B$1:D$42,3,FALSE) -> Service Operations Center | B141: =VLOOKUP(C141,Sheet3!A$1:B$42,2,FALSE) -> OP_NA_03 | C141: Service Problem Management | D141: 5.12 | E141: Service Trouble Tracking and Business Value Development | F141: 5.12.2 | G141: Service Trouble Lifecycle Management | H141: Service Trouble Lifecycle Management Function tracks and manages the events and the lifecycle related to the Service Trouble (for example when the resolution is ended), and assures that service troubles are assigned, coordinated, efficiently solved, and escalating as needed. It manages Service Trouble closure according to business rules: the service trouble can be closed as soon as a palliative action has been done and the user retrieved a not degraded use, and at least one Resource Trouble Ticket is still ongoing or only when the trouble is definitely treated - all associated Resource Trouble Tickets are closed.
A142: =VLOOKUP(B142,Sheet3!B$1:D$42,3,FALSE) -> Service Operations Center | B142: =VLOOKUP(C142,Sheet3!A$1:B$42,2,FALSE) -> OP_NA_04 | C142: Service Quality and Performance Management | D142: 5.13 | E142: Service Performance Development | F142: 5.13.1 | G142: Service Problem Monitoring Model Definition | H142: Service Problem Monitoring Model Definition designs the service problem monitoring model and its dependencies.
A143: =VLOOKUP(B143,Sheet3!B$1:D$42,3,FALSE) -> Service Operations Center | B143: =VLOOKUP(C143,Sheet3!A$1:B$42,2,FALSE) -> OP_NA_04 | C143: Service Quality and Performance Management | D143: 5.13 | E143: Service Performance Development | F143: 5.13.2 | G143: Service Problem Monitoring Model Establishing | H143: Service Problem Monitoring Model Establishing function provides establishment of models to derive, identify and mitigate Service Problems.
A144: =VLOOKUP(B144,Sheet3!B$1:D$42,3,FALSE) -> Service Operations Center | B144: =VLOOKUP(C144,Sheet3!A$1:B$42,2,FALSE) -> OP_NA_04 | C144: Service Quality and Performance Management | D144: 5.14 | E144: Service Quality Development | F144: 5.14.1 | G144: Service Quality Model Definition | H144: Service Quality Model Definition function defines the service quality model and its dependencies. It includes KQIs and SLOs specifications establishment.
A145: =VLOOKUP(B145,Sheet3!B$1:D$42,3,FALSE) -> Service Operations Center | B145: =VLOOKUP(C145,Sheet3!A$1:B$42,2,FALSE) -> OP_NA_04 | C145: Service Quality and Performance Management | D145: 5.15 | E145: Service Performance Management | F145: 5.15.1 | G145: Service Performance Planning | H145: Service Performance Planning provides the necessary functionality to perform near term (hours/days) tactical service performance planning. This includes the means to model and explore various "what if" scenarios. The results may then lead to a near term network adjustment (e.g. - reroute of traffic).
A146: =VLOOKUP(B146,Sheet3!B$1:D$42,3,FALSE) -> Service Operations Center | B146: =VLOOKUP(C146,Sheet3!A$1:B$42,2,FALSE) -> OP_NA_04 | C146: Service Quality and Performance Management | D146: 5.16 | E146: Service Quality and Performance Supervision | F146: 5.16.1 | G146: Service Performance Monitoring | H146: Service Performance Monitoring provides monitoring of service performance data including notification and accumulation for e.g. Service Performance Dashboard.
A147: =VLOOKUP(B147,Sheet3!B$1:D$42,3,FALSE) -> Service Operations Center | B147: =VLOOKUP(C147,Sheet3!A$1:B$42,2,FALSE) -> OP_NA_04 | C147: Service Quality and Performance Management | D147: 5.16 | E147: Service Quality and Performance Supervision | F147: 5.16.2 | G147: Service Problem SLA Monitoring | H147: Service Problem SLA Monitoring function compares the service problem status', severity and lapse of time against established service level agreements.
A148: =VLOOKUP(B148,Sheet3!B$1:D$42,3,FALSE) -> Service Operations Center | B148: =VLOOKUP(C148,Sheet3!A$1:B$42,2,FALSE) -> OP_NA_04 | C148: Service Quality and Performance Management | D148: 5.17 | E148: Service Quality and Performance Repository Management | F148: 5.17.1 | G148: Service Performance Reporting | H148: Service Performance Reporting provides the necessary functionality required to generate reports about the performance of the service provider\\'s services. These reports may be generated as part of the normal periodic operations ("scheduled"), or may be as a result of a specific analysis request ("in-demand"). Report types include near real time, historical view, and trend analysis. Relevant performance reports are also provided to service/network planning to perform network updates.
A149: =VLOOKUP(B149,Sheet3!B$1:D$42,3,FALSE) -> Service Operations Center | B149: =VLOOKUP(C149,Sheet3!A$1:B$42,2,FALSE) -> OP_NA_04 | C149: Service Quality and Performance Management | D149: 5.17 | E149: Service Quality and Performance Repository Management | F149: 5.17.2 | G149: Service Performance Data Collection | H149: Service Performance Data Collection collects Service Performance Data from the Resource Management functions related to a specific Service (or directly in the absence of Resource Performance Management function) and Collection of Service Performance data from the end-to-end tests done by the service test functions internally or from external Service Test applications. Includes archiving.
A150: =VLOOKUP(B150,Sheet3!B$1:D$42,3,FALSE) -> Service Operations Center | B150: =VLOOKUP(C150,Sheet3!A$1:B$42,2,FALSE) -> OP_NA_04 | C150: Service Quality and Performance Management | D150: 5.17 | E150: Service Quality and Performance Repository Management | F150: 5.17.3 | G150: Service Quality Collection & Monitoring | H150: Service Quality Collection & Monitoring collects service quality related information from established sources, including service performance management, service problem management, third parties, and customers. Collected data is logged for further analysis and monitored for direct notification in case of significant quality deviation.
A151: =VLOOKUP(B151,Sheet3!B$1:D$42,3,FALSE) -> Service Operations Center | B151: =VLOOKUP(C151,Sheet3!A$1:B$42,2,FALSE) -> OP_NA_04 | C151: Service Quality and Performance Management | D151: 5.17 | E151: Service Quality and Performance Repository Management | F151: 5.17.5 | G151: Service Quality Reporting | H151: Service Quality Reporting functions generate various reports on service quality and makes them available for consumption. E.g. Visual aids.
A152: =VLOOKUP(B152,Sheet3!B$1:D$42,3,FALSE) -> Service Operations Center | B152: =VLOOKUP(C152,Sheet3!A$1:B$42,2,FALSE) -> OP_NA_04 | C152: Service Quality and Performance Management | D152: 5.17 | E152: Service Quality and Performance Repository Management | F152: 5.17.6 | G152: Service Problem Monitoring Model Data Definition | H152: Accepting input from customer contracts, service definitions (KQIs, SLOs etc.) or changes in the service topology the function establishes the data the models needs for monitoring of services with respect to problems.
A153: =VLOOKUP(B153,Sheet3!B$1:D$42,3,FALSE) -> Service Operations Center | B153: =VLOOKUP(C153,Sheet3!A$1:B$42,2,FALSE) -> OP_NA_04 | C153: Service Quality and Performance Management | D153: 5.17 | E153: Service Quality and Performance Repository Management | F153: 5.17.7 | G153: Service Problem Monitoring Model Data Integration | H153: Establishment of data sources for monitoring of customer contracts, service definitions (KQIs, SLOs etc.) or changes in the service topology the function establishes the data the models needs for monitoring of services with respect to problems.
A154: =VLOOKUP(B154,Sheet3!B$1:D$42,3,FALSE) -> Service Operations Center | B154: =VLOOKUP(C154,Sheet3!A$1:B$42,2,FALSE) -> OP_NA_04 | C154: Service Quality and Performance Management | D154: 5.17 | E154: Service Quality and Performance Repository Management | F154: 5.17.8 | G154: Service Problem Messages Monitoring | H154: Service Problem Messages Monitoring is responsible for collecting status messages for further correlation and comparison to the topology and service monitoring model.
A155: =VLOOKUP(B155,Sheet3!B$1:D$42,3,FALSE) -> Service Operations Center | B155: =VLOOKUP(C155,Sheet3!A$1:B$42,2,FALSE) -> OP_NA_04 | C155: Service Quality and Performance Management | D155: 5.17 | E155: Service Quality and Performance Repository Management | F155: 5.17.9 | G155: Service Problem Correction Reporting | H155: Service Problem Correction Reporting and notification of correction status to applications and personnel responsible for problem mitigation of the services and resources.
A156: =VLOOKUP(B156,Sheet3!B$1:D$42,3,FALSE) -> Service Operations Center | B156: =VLOOKUP(C156,Sheet3!A$1:B$42,2,FALSE) -> OP_NA_02 | C156: Service Management | D156: 5.2 | E156: Service Repository Management | F156: 5.2.1 | G156: Onboarded Service Integration Configuration | H156: Onboarded Service Integration Configuration function will configure the on boarded service and the relevant systems to establish integration automatically, when requested. There are several system services in the infrastructure that needs to be aware and integrated with the new service.
A157: =VLOOKUP(B157,Sheet3!B$1:D$42,3,FALSE) -> Service Operations Center | B157: =VLOOKUP(C157,Sheet3!A$1:B$42,2,FALSE) -> OP_NA_02 | C157: Service Management | D157: 5.2 | E157: Service Repository Management | F157: 5.2.2 | G157: Service Data Retrieval | H157: Service Data Retrieval provides retrieval of appropriate inventory data for example in the context of service end to end testing.
A158: =VLOOKUP(B158,Sheet3!B$1:D$42,3,FALSE) -> Service Operations Center | B158: =VLOOKUP(C158,Sheet3!A$1:B$42,2,FALSE) -> OP_NA_02 | C158: Service Management | D158: 5.2 | E158: Service Repository Management | F158: 5.2.3 | G158: Service-Resource Relationship Management Notifications | H158: Notification of Service-Resource Relationship Management actions to relevant stakeholders.
A159: =VLOOKUP(B159,Sheet3!B$1:D$42,3,FALSE) -> Service Operations Center | B159: =VLOOKUP(C159,Sheet3!A$1:B$42,2,FALSE) -> OP_NA_02 | C159: Service Management | D159: 5.2 | E159: Service Repository Management | F159: 5.2.4 | G159: Service Repository Updating | H159: Service Repository Updating updates information in the service inventory according to the configuration of specific services.
A160: =VLOOKUP(B160,Sheet3!B$1:D$42,3,FALSE) -> Service Operations Center | B160: =VLOOKUP(C160,Sheet3!A$1:B$42,2,FALSE) -> OP_NA_02 | C160: Service Management | D160: 5.2 | E160: Service Repository Management | F160: 5.2.5 | G160: Service to Resource Relationship Management | H160: Service to Resource Relationship Management provides Creation, Update and Deletion of the relations of stand-alone physical or logical resources whose assignment is critical to service\\'s fulfillment, and whose tracking is critical to service operations, assurance, and billing, as well as, resources, which represent a larger resource structure supporting the service, often referred to as an Access Point.
A161: =VLOOKUP(B161,Sheet3!B$1:D$42,3,FALSE) -> Service Operations Center | B161: =VLOOKUP(C161,Sheet3!A$1:B$42,2,FALSE) -> OP_NA_02 | C161: Service Management | D161: 5.2 | E161: Service Repository Management | F161: 5.2.6 | G161: Service to Resource Relationship Synchronization | H161: Service to Resource Relationship Synchronization function entails reconciliation of the data in a Service Inventory Management system with inventory discovered from other sources and synchronizes mismatched service inventory records.
A162: =VLOOKUP(B162,Sheet3!B$1:D$42,3,FALSE) -> Service Operations Center | B162: =VLOOKUP(C162,Sheet3!A$1:B$42,2,FALSE) -> OP_NA_02 | C162: Service Management | D162: 5.2 | E162: Service Repository Management | F162: 5.2.7 | G162: Service Instance Lifecycle Management | H162: Service Instance Lifecycle Management function will control the starting of new instances and closing of instances of a service as well as other activity states of the service instances. Software based Services’ performance and availability may be controlled by managing multiple instances of the service with multiple states of activity.
A163: =VLOOKUP(B163,Sheet3!B$1:D$42,3,FALSE) -> Service Operations Center | B163: =VLOOKUP(C163,Sheet3!A$1:B$42,2,FALSE) -> OP_NA_02 | C163: Service Management | D163: 5.2 | E163: Service Repository Management | F163: 5.2.8 | G163: Service Topology Discovery | H163: Service Topology Discovery function provides the required capability to discover how resources (e.g. network) are related to each other in providing a service.
... A285: =VLOOKUP(B285,Sheet3!B$1:D$42,3,FALSE) -> Autonomous Operations | B285: =VLOOKUP(C285,Sheet3!A$1:B$42,2,FALSE) -> OP_AO_01 | C285: Autonomous Operations Platform and People | D285: 12.4 | E285: AO Technology Lifecycle Management | F285: 12.4.4 | G285: Maintenance | H285: Effective maintenance of AO projects with respect to Perfromance, Change Management and Availability.
A286: =VLOOKUP(B286,Sheet3!B$1:D$42,3,FALSE) -> Network Optimization | B286: =VLOOKUP(C286,Sheet3!A$1:B$42,2,FALSE) -> OP_NO_02 | C286: Network Optimization for RAN | D286: 10.3 | E286: 2G Radio Network Optimization | F286: 10.3.1 | G286: Identify Problem related to customer complaint | H286: Collect statistics data from OSS, drive test reports and results of prior actions. Analyse to identify the problem and optimization steps.
A287: =VLOOKUP(B287,Sheet3!B$1:D$42,3,FALSE) -> Network Optimization | B287: =VLOOKUP(C287,Sheet3!A$1:B$42,2,FALSE) -> OP_NO_02 | C287: Network Optimization for RAN | D287: 10.3 | E287: 2G Radio Network Optimization | F287: 10.3.2 | G287: Analyse customer complaint and network problem | H287: Collect statistics data from OSS, drive test reports and results of prior actions. Analyse to identify the problem and optimization steps.
A288: =VLOOKUP(B288,Sheet3!B$1:D$42,3,FALSE) -> Network Optimization | B288: =VLOOKUP(C288,Sheet3!A$1:B$42,2,FALSE) -> OP_NO_02 | C288: Network Optimization for RAN | D288: 10.3 | E288: 2G Radio Network Optimization | F288: 10.3.3 | G288: Optimization solution | H288: Evaluate best solution for improvement and the potential impact when applying the optimization solution.
A289: =VLOOKUP(B289,Sheet3!B$1:D$42,3,FALSE) -> Network Optimization | B289: =VLOOKUP(C289,Sheet3!A$1:B$42,2,FALSE) -> OP_NO_02 | C289: Network Optimization for RAN | D289: 10.3 | E289: 2G Radio Network Optimization | F289: 10.3.4 | G289: Solution Implementation | H289: Make optimization plan details about actions to be taken, solution implementation and verifications steps that improvement has happened.
A290: =VLOOKUP(B290,Sheet3!B$1:D$42,3,FALSE) -> Network Optimization | B290: =VLOOKUP(C290,Sheet3!A$1:B$42,2,FALSE) -> OP_NO_02 | C290: Network Optimization for RAN | D290: 10.3 | E290: 2G Radio Network Optimization | F290: 10.3.5 | G290: Evaluate results and summerize | H290: Using data from OSS, drive test, compare and make detailed report of performance KPI before and after applying the solution. Summerize problem and solution in detail to prevent problem from happening again.
A291: =VLOOKUP(B291,Sheet3!B$1:D$42,3,FALSE) -> Network Optimization | B291: =VLOOKUP(C291,Sheet3!A$1:B$42,2,FALSE) -> OP_NO_02 | C291: Network Optimization for RAN | D291: 10.4 | E291: 3G Radio Network Optimization | F291: 10.4.1 | G291: Identify Problem related to customer complaint | H291: Collect statistics data from OSS, drive test reports and results of prior actions. Analyse to identify the problem and optimization steps.
A292: =VLOOKUP(B292,Sheet3!B$1:D$42,3,FALSE) -> Network Optimization | B292: =VLOOKUP(C292,Sheet3!A$1:B$42,2,FALSE) -> OP_NO_02 | C292: Network Optimization for RAN | D292: 10.4 | E292: 3G Radio Network Optimization | F292: 10.4.2 | G292: Analyse customer complaint and network problem | H292: Collect statistics data from OSS, drive test reports and results of prior actions. Analyse to identify the problem and optimization steps.
A293: =VLOOKUP(B293,Sheet3!B$1:D$42,3,FALSE) -> Network Optimization | B293: =VLOOKUP(C293,Sheet3!A$1:B$42,2,FALSE) -> OP_NO_02 | C293: Network Optimization for RAN | D293: 10.4 | E293: 3G Radio Network Optimization | F293: 10.4.3 | G293: Optimization solution | H293: Evaluate best solution for improvement and the potential impact when applying the optimization solution.
A294: =VLOOKUP(B294,Sheet3!B$1:D$42,3,FALSE) -> Network Optimization | B294: =VLOOKUP(C294,Sheet3!A$1:B$42,2,FALSE) -> OP_NO_02 | C294: Network Optimization for RAN | D294: 10.4 | E294: 3G Radio Network Optimization | F294: 10.4.4 | G294: Solution Implementation | H294: Make optimization plan details about actions to be taken, solution implementation and verifications steps that improvement has happened.
A295: =VLOOKUP(B295,Sheet3!B$1:D$42,3,FALSE) -> Network Optimization | B295: =VLOOKUP(C295,Sheet3!A$1:B$42,2,FALSE) -> OP_NO_02 | C295: Network Optimization for RAN | D295: 10.4 | E295: 3G Radio Network Optimization | F295: 10.4.5 | G295: Evaluate results and summerize | H295: Using data from OSS, drive test, compare and make detailed report of performance KPI before and after applying the solution. Summerize problem and solution in detail to prevent problem from happening again.
A296: =VLOOKUP(B296,Sheet3!B$1:D$42,3,FALSE) -> Network Optimization | B296: =VLOOKUP(C296,Sheet3!A$1:B$42,2,FALSE) -> OP_NO_02 | C296: Network Optimization for RAN | D296: 10.5 | E296: 4G Radio Network Optimization | F296: 10.5.1 | G296: Identify Problem related to customer complaint | H296: Collect statistics data from OSS, drive test reports and results of prior actions. Analyse to identify the problem and optimization steps.
A297: =VLOOKUP(B297,Sheet3!B$1:D$42,3,FALSE) -> Network Optimization | B297: =VLOOKUP(C297,Sheet3!A$1:B$42,2,FALSE) -> OP_NO_02 | C297: Network Optimization for RAN | D297: 10.5 | E297: 4G Radio Network Optimization | F297: 10.5.2 | G297: Analyse customer complaint and network problem | H297: Collect statistics data from OSS, drive test reports and results of prior actions. Analyse to identify the problem and optimization steps.
... A383: =VLOOKUP(B383,Sheet3!B$1:D$42,3,FALSE) -> Network Operations Center | B383: =VLOOKUP(C383,Sheet3!A$1:B$42,2,FALSE) -> OP_NOC_8 | C383: E2E Network Performance Management | D383: 6.24 | E383: E2E Performance Monitoring | F383: 6.24.1 | G383: Network End-To-End Performance Monitoring | H383: Network End-To-End Performance Supervision provides integration with ERP applications for End – End supervising the Network performance.

Sheet Sheet3
A1: Customer Experience Management | B1: OP_CX_01 | C1: =LEFT(B1,5) -> OP_CX | D1: =VLOOKUP(C1,Sheet2!A$1:B$10,2,FALSE) -> Customer Experience
A2: Customer Information Management | B2: OP_CX_02 | C2: =LEFT(B2,5) -> OP_CX | D2: =VLOOKUP(C2,Sheet2!A$1:B$10,2,FALSE) -> Customer Experience
A3: Customer Order Management | B3: OP_CX_03 | C3: =LEFT(B3,5) -> OP_CX | D3: =VLOOKUP(C3,Sheet2!A$1:B$10,2,FALSE) -> Customer Experience
A4: Customer Behavior Analysis | B4: OP_CX_04 | C4: =LEFT(B4,5) -> OP_CX | D4: =VLOOKUP(C4,Sheet2!A$1:B$10,2,FALSE) -> Customer Experience
A5: Asset Management | B5: OP_FO_01 | C5: =LEFT(B5,5) -> OP_FO | D5: =VLOOKUP(C5,Sheet2!A$1:B$10,2,FALSE) -> Field Operations
A6: Work Order Management | B6: OP_FO_02 | C6: =LEFT(B6,5) -> OP_FO | D6: =VLOOKUP(C6,Sheet2!A$1:B$10,2,FALSE) -> Field Operations
A7: Inventory Management | B7: OP_IM_01 | C7: =LEFT(B7,5) -> OP_IM | D7: =VLOOKUP(C7,Sheet2!A$1:B$10,2,FALSE) -> Inventory Management
A8: Supply Chain Fulfillment | B8: OP_IM_02 | C8: =LEFT(B8,5) -> OP_IM | D8: =VLOOKUP(C8,Sheet2!A$1:B$10,2,FALSE) -> Inventory Management
A9: Network Planning | B9: OP_TM_01 | C9: =LEFT(B9,5) -> OP_TM | D9: =VLOOKUP(C9,Sheet2!A$1:B$10,2,FALSE) -> Network Planning and Deployment
A10: Network Deployment | B10: OP_TM_02 | C10: =LEFT(B10,5) -> OP_TM | D10: =VLOOKUP(C10,Sheet2!A$1:B$10,2,FALSE) -> Network Planning and Deployment
A11: Network Topology Management | B11: OP_TM_03 | C11: =LEFT(B11,5) -> OP_TM | D11: =VLOOKUP(C11,Sheet2!A$1:B$10,2,FALSE) -> Network Planning and Deployment
A12: Service Analysis | B12: OP_NA_01 | C12: =LEFT(B12,5) -> OP_NA | D12: =VLOOKUP(C12,Sheet2!A$1:B$10,2,FALSE) -> Service Operations Center
... A15: Service Quality and Performance Management | B15: OP_NA_04 | C15: =LEFT(B15,5) -> OP_NA | D15: =VLOOKUP(C15,Sheet2!A$1:B$10,2,FALSE) -> Service Operations Center
A16: RAN Network Performance Management | B16: OP_NOC_1 | C16: =LEFT(B16,6) -> OP_NOC | D16: =VLOOKUP(C16,Sheet2!A$1:B$10,2,FALSE) -> Network Operations Center
A17: RAN Network Trouble Management | B17: OP_NOC_2 | C17: =LEFT(B17,6) -> OP_NOC | D17: =VLOOKUP(C17,Sheet2!A$1:B$10,2,FALSE) -> Network Operations Center
A18: Core Network Performance Management | B18: OP_NOC_3 | C18: =LEFT(B18,6) -> OP_NOC | D18: =VLOOKUP(C18,Sheet2!A$1:B$10,2,FALSE) -> Network Operations Center
A19: Core Network Trouble Management | B19: OP_NOC_4 | C19: =LEFT(B19,6) -> OP_NOC | D19: =VLOOKUP(C19,Sheet2!A$1:B$10,2,FALSE) -> Network Operations Center
A20: IP Network Performance Management | B20: OP_NOC_5 | C20: =LEFT(B20,6) -> OP_NOC | D20: =VLOOKUP(C20,Sheet2!A$1:B$10,2,FALSE) -> Network Operations Center
A21: IP and Backhaul Network Trouble Management | B21: OP_NOC_6 | C21: =LEFT(B21,6) -> OP_NOC | D21: =VLOOKUP(C21,Sheet2!A$1:B$10,2,FALSE) -> Network Operations Center
A22: Network Usage Management | B22: OP_NOC_7 | C22: =LEFT(B22,6) -> OP_NOC | D22: =VLOOKUP(C22,Sheet2!A$1:B$10,2,FALSE) -> Network Operations Center
A23: E2E Network Performance Management | B23: OP_NOC_8 | C23: =LEFT(B23,6) -> OP_NOC | D23: =VLOOKUP(C23,Sheet2!A$1:B$10,2,FALSE) -> Network Operations Center
A24: Network Capacity Management | B24: OP_NO_01 | C24: =LEFT(B24,5) -> OP_NO | D24: =VLOOKUP(C24,Sheet2!A$1:B$10,2,FALSE) -> Network Optimization
A25: Network Optimization for RAN | B25: OP_NO_02 | C25: =LEFT(B25,5) -> OP_NO | D25: =VLOOKUP(C25,Sheet2!A$1:B$10,2,FALSE) -> Network Optimization
A26: Network Optimization for Core | B26: OP_NO_03 | C26: =LEFT(B26,5) -> OP_NO | D26: =VLOOKUP(C26,Sheet2!A$1:B$10,2,FALSE) -> Network Optimization
A27: Network Optimization for IP and Backhaul | B27: OP_NO_04 | C27: =LEFT(B27,5) -> OP_NO | D27: =VLOOKUP(C27,Sheet2!A$1:B$10,2,FALSE) -> Network Optimization
A28: Network Optimization for QoE | B28: OP_NO_05 | C28: =LEFT(B28,5) -> OP_NO | D28: =VLOOKUP(C28,Sheet2!A$1:B$10,2,FALSE) -> Network Optimization
A29: Network Traffic Management | B29: OP_NO_06 | C29: =LEFT(B29,5) -> OP_NO | D29: =VLOOKUP(C29,Sheet2!A$1:B$10,2,FALSE) -> Network Optimization
A30: Anomaly Detection | B30: OP_NO_07 | C30: =LEFT(B30,5) -> OP_NO | D30: =VLOOKUP(C30,Sheet2!A$1:B$10,2,FALSE) -> Network Optimization
A31: Product and Service Configuration & Activation | B31: OP_SO_01 | C31: =LEFT(B31,5) -> OP_SO | D31: =VLOOKUP(C31,Sheet2!A$1:B$10,2,FALSE) -> Products and Services
A32: Product and Service Operational Analysis | B32: OP_SO_02 | C32: =LEFT(B32,5) -> OP_SO | D32: =VLOOKUP(C32,Sheet2!A$1:B$10,2,FALSE) -> Products and Services
A33: Product and Service Performance Management | B33: OP_SO_03 | C33: =LEFT(B33,5) -> OP_SO | D33: =VLOOKUP(C33,Sheet2!A$1:B$10,2,FALSE) -> Products and Services
A34: Product and Service Problem Management | B34: OP_SO_04 | C34: =LEFT(B34,5) -> OP_SO | D34: =VLOOKUP(C34,Sheet2!A$1:B$10,2,FALSE) -> Products and Services
A35: Security Management | B35: OP_SO_05 | C35: =LEFT(B35,5) -> OP_SO | D35: =VLOOKUP(C35,Sheet2!A$1:B$10,2,FALSE) -> Products and Services
... A42: Engagement of Smart Things | B42: OP_OT_03 | C42: =LEFT(B42,5) -> OP_OT | D42: =VLOOKUP(C42,Sheet2!A$1:B$10,2,FALSE) -> Other Topics

Sheet Sheet2
A1: OP_TM | B1: Network Planning and Deployment
A2: OP_NOC | B2: Network Operations Center
A3: OP_NA | B3: Service Operations Center
A4: OP_FO | B4: Field Operations
A5: OP_IM | B5: Inventory Management
A6: OP_SO | B6: Products and Services
A7: OP_CX | B7: Customer Experience
A8: OP_NO | B8: Network Optimization
A9: OP_AO | B9: Autonomous Operations
A10: OP_OT | B10: Other Topics
